treeline/__init__.py
treeline/cli.py
treeline/config.py
treeline/domain.py
treeline/theme.py
treeline/utils.py
treeline/abstractions/__init__.py
treeline/abstractions/backup.py
treeline/abstractions/data.py
treeline/abstractions/db.py
treeline/app/__init__.py
treeline/app/account_service.py
treeline/app/backfill_service.py
treeline/app/backup_service.py
treeline/app/container.py
treeline/app/db_service.py
treeline/app/doctor_service.py
treeline/app/encryption_service.py
treeline/app/import_service.py
treeline/app/integration_service.py
treeline/app/plugin_service.py
treeline/app/preferences_service.py
treeline/app/status_service.py
treeline/app/sync_service.py
treeline/app/tagging_service.py
treeline/commands/__init__.py
treeline/commands/backfill.py
treeline/commands/backup.py
treeline/commands/compact.py
treeline/commands/demo.py
treeline/commands/doctor.py
treeline/commands/encrypt.py
treeline/commands/import_cmd.py
treeline/commands/new.py
treeline/commands/plugin.py
treeline/commands/query.py
treeline/commands/remove.py
treeline/commands/setup.py
treeline/commands/status.py
treeline/commands/sync.py
treeline/commands/tag.py
treeline/infra/__init__.py
treeline/infra/csv.py
treeline/infra/demo.py
treeline/infra/duckdb.py
treeline/infra/local_backup.py
treeline/infra/simplefin.py
treeline/infra/migrations/000_migrations.sql
treeline/infra/migrations/001_initial_schema.sql
treeline/infra/migrations/002_transaction_editing.sql
treeline/infra/migrations/003_plugin_budget.sql
treeline/infra/migrations/004_budget_month_scoped.sql
treeline/infra/migrations/005_plugin_transactions_rules.sql
treeline/infra/migrations/006_plugin_accounts_query.sql
treeline/infra/migrations/007_balance_snapshot_source.sql
treeline/infra/migrations/008_simplify_tag_rules.sql
treeline/infra/migrations/009_plugin_schemas.sql
treeline/infra/migrations/010_plugin_accounts_schema.sql
treeline/themes/default.json
treeline_money-0.1.66.dist-info/METADATA
treeline_money-0.1.66.dist-info/WHEEL
treeline_money-0.1.66.dist-info/entry_points.txt
treeline_money-0.1.66.dist-info/top_level.txt
treeline_money-0.1.66.dist-info/RECORD
