Metadata-Version: 2.4
Name: treeline-money
Version: 0.1.66
Summary: Personal finance in your terminal
Author: Zack Schrag
License: MIT
Project-URL: Homepage, https://github.com/treeline-money/treeline
Project-URL: Repository, https://github.com/treeline-money/treeline
Project-URL: Issues, https://github.com/treeline-money/treeline/issues
Keywords: personal-finance,cli,duckdb,sql,finance,banking,transactions,simplefin,budget,money
Classifier: Development Status :: 4 - Beta
Classifier: Environment :: Console
Classifier: Intended Audience :: End Users/Desktop
Classifier: Intended Audience :: Developers
Classifier: License :: OSI Approved :: MIT License
Classifier: Operating System :: OS Independent
Classifier: Programming Language :: Python :: 3
Classifier: Programming Language :: Python :: 3.12
Classifier: Programming Language :: Python :: 3.13
Classifier: Topic :: Office/Business :: Financial
Classifier: Topic :: Utilities
Classifier: Typing :: Typed
Requires-Python: >=3.12
Requires-Dist: argon2-cffi>=23.1.0
Requires-Dist: duckdb>=1.4.0
Requires-Dist: httpx>=0.28.1
Requires-Dist: prompt-toolkit>=3.0.52
Requires-Dist: pydantic>=2.11.9
Requires-Dist: python-dotenv>=1.1.1
Requires-Dist: pytz>=2025.2
Requires-Dist: readchar>=4.2.1
Requires-Dist: rich>=14.1.0
Requires-Dist: typer>=0.19.2
